probeinterface/__init__.py
probeinterface/generator.py
probeinterface/io.py
probeinterface/library.py
probeinterface/neuropixels_tools.py
probeinterface/plotting.py
probeinterface/probe.py
probeinterface/probegroup.py
probeinterface/shank.py
probeinterface/testing.py
probeinterface/utils.py
probeinterface/wiring.py
probeinterface/resources/neuropixels_probe_features.json
probeinterface/schema/probe.json.schema
probeinterface-0.3.1.dist-info/METADATA
probeinterface-0.3.1.dist-info/WHEEL
probeinterface-0.3.1.dist-info/licenses/LICENSE
probeinterface-0.3.1.dist-info/RECORD
