Metadata-Version: 2.4
Name: probeinterface
Version: 0.3.1
Summary: Python package to handle probe layout, geometry and wiring to device.
Project-URL: homepage, https://github.com/SpikeInterface/probeinterface
Project-URL: repository, https://github.com/SpikeInterface/probeinterface
Project-URL: documentation, https://probeinterface.readthedocs.io
Project-URL: changelog, https://probeinterface.readthedocs.io/en/main/release_notes.html
Author-email: Samuel Garcia <sam.garcia.die@gmail.com>, Alessio Buccino <alessiop.buccino@gmail.com>
License-File: LICENSE
Classifier: License :: OSI Approved :: MIT License
Classifier: Operating System :: OS Independent
Classifier: Programming Language :: Python :: 3
Requires-Python: >=3.9
Requires-Dist: numpy
Requires-Dist: packaging
Requires-Dist: requests
Provides-Extra: docs
Requires-Dist: matplotlib==3.2.2; extra == 'docs'
Requires-Dist: pandas; extra == 'docs'
Requires-Dist: pillow; extra == 'docs'
Requires-Dist: scipy; extra == 'docs'
Requires-Dist: sphinx-gallery; extra == 'docs'
Requires-Dist: sphinx-rtd-theme; extra == 'docs'
Provides-Extra: test
Requires-Dist: h5py; extra == 'test'
Requires-Dist: jsonschema; extra == 'test'
Requires-Dist: matplotlib; extra == 'test'
Requires-Dist: pandas; extra == 'test'
Requires-Dist: pytest; extra == 'test'
Requires-Dist: pytest-cov; extra == 'test'
Requires-Dist: scipy; extra == 'test'
Requires-Dist: zarr<3.0.0,>=2.16.0; extra == 'test'
